[
 {
   "Cap": 39,
   "#": 20,
   "Player": "Black, Simon",
   "DOB": "3/04/1979",
   "HT": "186cm",
   "WT": "81kg",
   "Games (W-D-L)": "322 (174-4-144)",
   "Goals": 171,
   "Seasons": "1998-2013",
   "Debut": "18y 359d",
   "Last": "34y 136d"
 },
 {
   "Cap": 42,
   "#": 6,
   "Player": "Power, Luke",
   "DOB": "8/01/1980",
   "HT": "179cm",
   "WT": "78kg",
   "Games (W-D-L)": "282 (152-3-127)",
   "Goals": 226,
   "Seasons": "1998-2011",
   "Debut": "18y 86d",
   "Last": "31y 231d"
 },
 {
   "Cap": 114,
   "#": 10,
   "Player": "Rich, Daniel",
   "DOB": "7/06/1990",
   "HT": "183cm",
   "WT": "87kg",
   "Games (W-D-L)": "275 (120-1-154)",
   "Goals": 116,
   "Seasons": "2009-2023",
   "Debut": "18y 294d",
   "Last": "33y 3d"
 },
 {
   "Cap": 56,
   "#": 16,
   "Player": "Brown, Jonathan",
   "DOB": "29/10/1981",
   "HT": "195cm",
   "WT": "103kg",
   "Games (W-D-L)": "256 (145-3-108)",
   "Goals": 594,
   "Seasons": "2000-2014",
   "Debut": "18y 162d",
   "Last": "32y 228d"
 },
 {
   "Cap": 143,
   "#": 15,
   "Player": "Zorko, Dayne",
   "DOB": "9/02/1989",
   "HT": "175cm",
   "WT": "78kg",
   "Games (W-D-L)": "250 (116-0-134)",
   "Goals": 224,
   "Seasons": "2012-2023",
   "Debut": "23y 93d",
   "Last": "34y 233d"
 },
 {
   "Cap": 34,
   "#": 36,
   "Player": "Bradshaw, Daniel",
   "DOB": "21/11/1978",
   "HT": "191cm",
   "WT": "95kg",
   "Games (W-D-L)": "219 (122-3-94)",
   "Goals": 496,
   "Seasons": "1997-1998, 2000-2006, 2008-2009",
   "Debut": "18y 178d",
   "Last": "30y 294d"
 },
 {
   "Cap": 11,
   "#": 44,
   "Player": "Lappin, Nigel",
   "DOB": "21/06/1976",
   "HT": "188cm",
   "WT": "87kg",
   "Games (W-D-L)": "218 (130-5-83)",
   "Goals": 134,
   "Seasons": "1997-2005, 2007-2008",
   "Debut": "20y 282d",
   "Last": "31y 296d"
 },
 {
   "Cap": 66,
   "#": 9,
   "Player": "McGrath, Ashley",
   "DOB": "20/05/1983",
   "HT": "183cm",
   "WT": "86kg",
   "Games (W-D-L)": "214 (103-2-109)",
   "Goals": 170,
   "Seasons": "2001-2014",
   "Debut": "18y 91d",
   "Last": "31y 96d"
 },
 {
   "Cap": 20,
   "#": 3,
   "Player": "Voss, Michael",
   "DOB": "7/07/1975",
   "HT": "183cm",
   "WT": "88kg",
   "Games (W-D-L)": "210 (129-1-80)",
   "Goals": 173,
   "Seasons": "1997-2006",
   "Debut": "21y 266d",
   "Last": "31y 57d"
 },
 {
   "Cap": 25,
   "#": 12,
   "Player": "Akermanis, Jason",
   "DOB": "24/02/1977",
   "HT": "177cm",
   "WT": "85kg",
   "Games (W-D-L)": "210 (128-3-79)",
   "Goals": 263,
   "Seasons": "1997-2006",
   "Debut": "20y 48d",
   "Last": "29y 141d"
 },
 {
   "Cap": 46,
   "#": 8,
   "Player": "Notting, Tim",
   "DOB": "21/10/1978",
   "HT": "188cm",
   "WT": "90kg",
   "Games (W-D-L)": "208 (121-4-83)",
   "Goals": 138,
   "Seasons": "1998-2009",
   "Debut": "19y 206d",
   "Last": "30y 325d"
 },
 {
   "Cap": 75,
   "#": 7,
   "Player": "Adcock, Jed",
   "DOB": "15/11/1985",
   "HT": "183cm",
   "WT": "83kg",
   "Games (W-D-L)": "206 (79-2-125)",
   "Goals": 59,
   "Seasons": "2004-2015",
   "Debut": "18y 175d",
   "Last": "29y 294d"
 },
 {
   "Cap": 8,
   "#": 2,
   "Player": "Johnson, Chris",
   "DOB": "30/05/1976",
   "HT": "180cm",
   "WT": "89kg",
   "Games (W-D-L)": "205 (120-5-80)",
   "Goals": 105,
   "Seasons": "1997-2007",
   "Debut": "20y 304d",
   "Last": "31y 94d"
 },
 {
   "Cap": 81,
   "#": 21,
   "Player": "Merrett, Daniel",
   "DOB": "12/12/1984",
   "HT": "195cm",
   "WT": "103kg",
   "Games (W-D-L)": "200 (79-3-118)",
   "Goals": 70,
   "Seasons": "2005-2016",
   "Debut": "20y 111d",
   "Last": "31y 260d"
 },
 {
   "Cap": 171,
   "#": 31,
   "Player": "Andrews, Harris",
   "DOB": "11/12/1996",
   "HT": "201cm",
   "WT": "100kg",
   "Games (W-D-L)": "186 (89-0-97)",
   "Goals": 11,
   "Seasons": "2015-2023",
   "Debut": "18y 128d",
   "Last": "26y 293d"
 },
 {
   "Cap": 12,
   "#": 23,
   "Player": "Leppitsch, Justin",
   "DOB": "1/10/1975",
   "HT": "191cm",
   "WT": "97kg",
   "Games (W-D-L)": "183 (113-3-67)",
   "Goals": 136,
   "Seasons": "1997-2006",
   "Debut": "21y 180d",
   "Last": "30y 218d"
 },
 {
   "Cap": 97,
   "#": 24,
   "Player": "Patfull, Joel",
   "DOB": "7/12/1984",
   "HT": "190cm",
   "WT": "90kg",
   "Games (W-D-L)": "182 (73-3-106)",
   "Goals": 24,
   "Seasons": "2006-2014",
   "Debut": "21y 165d",
   "Last": "29y 266d"
 },
 {
   "Cap": 131,
   "#": 35,
   "Player": "Lester, Ryan",
   "DOB": "26/08/1992",
   "HT": "192cm",
   "WT": "85kg",
   "Games (W-D-L)": "180 (81-0-99)",
   "Goals": 47,
   "Seasons": "2011-2023",
   "Debut": "18y 212d",
   "Last": "31y 35d"
 },
 {
   "Cap": 21,
   "#": 33,
   "Player": "White, Darryl",
   "DOB": "12/06/1973",
   "HT": "189cm",
   "WT": "85kg",
   "Games (W-D-L)": "178 (106-3-69)",
   "Goals": 59,
   "Seasons": "1997-2005",
   "Debut": "23y 291d",
   "Last": "32y 76d"
 },
 {
   "Cap": 7,
   "#": 32,
   "Player": "Hart, Shaun",
   "DOB": "17/05/1971",
   "HT": "175cm",
   "WT": "74kg",
   "Games (W-D-L)": "171 (110-2-59)",
   "Goals": 96,
   "Seasons": "1997-2004",
   "Debut": "25y 317d",
   "Last": "33y 124d"
 },
 {
   "Cap": 1,
   "#": 10,
   "Player": "Ashcroft, Marcus",
   "DOB": "25/09/1971",
   "HT": "184cm",
   "WT": "83kg",
   "Games (W-D-L)": "166 (100-3-63)",
   "Goals": 61,
   "Seasons": "1997-2003",
   "Debut": "25y 186d",
   "Last": "32y 2d"
 },
 {
   "Cap": 164,
   "#": 25,
   "Player": "McStay, Daniel",
   "DOB": "24/06/1995",
   "HT": "195cm",
   "WT": "100kg",
   "Games (W-D-L)": "161 (78-0-83)",
   "Goals": 138,
   "Seasons": "2014-2022",
   "Debut": "19y 4d",
   "Last": "27y 84d"
 },
 {
   "Cap": 30,
   "#": 22,
   "Player": "Scott, Chris",
   "DOB": "3/05/1976",
   "HT": "182cm",
   "WT": "90kg",
   "Games (W-D-L)": "160 (99-2-59)",
   "Goals": 56,
   "Seasons": "1997-2005, 2007",
   "Debut": "21y",
   "Last": "31y 121d"
 },
 {
   "Cap": 161,
   "#": 27,
   "Player": "Gardiner, Darcy",
   "DOB": "22/09/1995",
   "HT": "193cm",
   "WT": "92kg",
   "Games (W-D-L)": "158 (73-0-85)",
   "Goals": 5,
   "Seasons": "2014-2023",
   "Debut": "18y 207d",
   "Last": "28y 8d"
 },
 {
   "Cap": 26,
   "#": 4,
   "Player": "McRae, Craig",
   "DOB": "22/09/1973",
   "HT": "176cm",
   "WT": "72kg",
   "Games (W-D-L)": "156 (104-2-50)",
   "Goals": 176,
   "Seasons": "1997-2004",
   "Debut": "23y 203d",
   "Last": "31y 3d"
 },
 {
   "Cap": 190,
   "#": 6,
   "Player": "McCluggage, Hugh",
   "DOB": "3/03/1998",
   "HT": "187cm",
   "WT": "85kg",
   "Games (W-D-L)": "155 (88-0-67)",
   "Goals": 97,
   "Seasons": "2017-2023",
   "Debut": "19y 37d",
   "Last": "25y 211d"
 },
 {
   "Cap": 13,
   "#": 11,
   "Player": "Lynch, Alastair",
   "DOB": "19/06/1968",
   "HT": "193cm",
   "WT": "97kg",
   "Games (W-D-L)": "154 (100-2-52)",
   "Goals": 371,
   "Seasons": "1997-2004",
   "Debut": "28y 284d",
   "Last": "36y 98d"
 },
 {
   "Cap": 119,
   "#": 38,
   "Player": "Rockliff, Tom",
   "DOB": "22/02/1990",
   "HT": "185cm",
   "WT": "85kg",
   "Games (W-D-L)": "154 (46-0-108)",
   "Goals": 87,
   "Seasons": "2009-2017",
   "Debut": "19y 160d",
   "Last": "27y 185d"
 },
 {
   "Cap": 182,
   "#": 30,
   "Player": "Hipwood, Eric",
   "DOB": "13/09/1997",
   "HT": "204cm",
   "WT": "90kg",
   "Games (W-D-L)": "153 (82-0-71)",
   "Goals": 229,
   "Seasons": "2016-2023",
   "Debut": "18y 279d",
   "Last": "26y 17d"
 },
 {
   "Cap": 170,
   "#": 5,
   "Player": "Robinson, Mitch",
   "DOB": "7/06/1989",
   "HT": "184cm",
   "WT": "90kg",
   "Games (W-D-L)": "147 (66-0-81)",
   "Goals": 71,
   "Seasons": "2015-2022",
   "Debut": "25y 301d",
   "Last": "33y 86d"
 },
 {
   "Cap": 40,
   "#": 5,
   "Player": "Scott, Brad",
   "DOB": "3/05/1976",
   "HT": "181cm",
   "WT": "87kg",
   "Games (W-D-L)": "146 (86-2-58)",
   "Goals": 39,
   "Seasons": "1998-1999, 2001-2006",
   "Debut": "21y 329d",
   "Last": "30y 122d"
 },
 {
   "Cap": 65,
   "#": 30,
   "Player": "Copeland, Robert",
   "DOB": "26/05/1981",
   "HT": "187cm",
   "WT": "85kg",
   "Games (W-D-L)": "143 (83-2-58)",
   "Goals": 39,
   "Seasons": "2001-2008",
   "Debut": "20y",
   "Last": "27y 89d"
 },
 {
   "Cap": 61,
   "#": 15,
   "Player": "Michael, Mal",
   "DOB": "24/06/1977",
   "HT": "190cm",
   "WT": "100kg",
   "Games (W-D-L)": "140 (89-1-50)",
   "Goals": 5,
   "Seasons": "2001-2006",
   "Debut": "23y 280d",
   "Last": "29y 70d"
 },
 {
   "Cap": 147,
   "#": 12,
   "Player": "Martin, Stefan",
   "DOB": "17/11/1986",
   "HT": "199cm",
   "WT": "104kg",
   "Games (W-D-L)": "133 (44-0-89)",
   "Goals": 23,
   "Seasons": "2013-2020",
   "Debut": "26y 133d",
   "Last": "33y 335d"
 },
 {
   "Cap": 189,
   "#": 7,
   "Player": "Berry, Jarrod",
   "DOB": "5/02/1998",
   "HT": "193cm",
   "WT": "89kg",
   "Games (W-D-L)": "133 (75-0-58)",
   "Goals": 58,
   "Seasons": "2017-2023",
   "Debut": "19y 63d",
   "Last": "25y 237d"
 },
 {
   "Cap": 64,
   "#": 19,
   "Player": "Charman, Jamie",
   "DOB": "16/07/1982",
   "HT": "197cm",
   "WT": "102kg",
   "Games (W-D-L)": "129 (74-3-52)",
   "Goals": 55,
   "Seasons": "2001-2009",
   "Debut": "18y 287d",
   "Last": "26y 275d"
 },
 {
   "Cap": 113,
   "#": 11,
   "Player": "Hanley, Pearce",
   "DOB": "15/11/1988",
   "HT": "185cm",
   "WT": "86kg",
   "Games (W-D-L)": "129 (38-0-91)",
   "Goals": 58,
   "Seasons": "2008-2016",
   "Debut": "19y 282d",
   "Last": "27y 287d"
 },
 {
   "Cap": 118,
   "#": 30,
   "Player": "Redden, Jack",
   "DOB": "9/12/1990",
   "HT": "190cm",
   "WT": "85kg",
   "Games (W-D-L)": "129 (44-1-84)",
   "Goals": 52,
   "Seasons": "2009-2015",
   "Debut": "18y 214d",
   "Last": "24y 256d"
 },
 {
   "Cap": 195,
   "#": 23,
   "Player": "Cameron, Charlie",
   "DOB": "5/07/1994",
   "HT": "181cm",
   "WT": "74kg",
   "Games (W-D-L)": "129 (83-0-46)",
   "Goals": 273,
   "Seasons": "2018-2023",
   "Debut": "23y 262d",
   "Last": "29y 87d"
 },
 {
   "Cap": 199,
   "#": 46,
   "Player": "McInerney, Oscar",
   "DOB": "10/07/1994",
   "HT": "205cm",
   "WT": "107kg",
   "Games (W-D-L)": "126 (80-0-46)",
   "Goals": 54,
   "Seasons": "2018-2023",
   "Debut": "23y 292d",
   "Last": "29y 82d"
 },
 {
   "Cap": 9,
   "#": 27,
   "Player": "Keating, Clark",
   "DOB": "19/03/1976",
   "HT": "197cm",
   "WT": "100kg",
   "Games (W-D-L)": "125 (78-1-46)",
   "Goals": 74,
   "Seasons": "1997-1999, 2001-2006",
   "Debut": "21y 11d",
   "Last": "30y 167d"
 },
 {
   "Cap": 71,
   "#": 17,
   "Player": "Brennan, Jared",
   "DOB": "28/07/1984",
   "HT": "192cm",
   "WT": "95kg",
   "Games (W-D-L)": "119 (55-3-61)",
   "Goals": 75,
   "Seasons": "2003-2010",
   "Debut": "18y 263d",
   "Last": "26y 31d"
 },
 {
   "Cap": 198,
   "#": 33,
   "Player": "Bailey, Zac",
   "DOB": "23/09/1999",
   "HT": "182cm",
   "WT": "83kg",
   "Games (W-D-L)": "118 (78-0-40)",
   "Goals": 121,
   "Seasons": "2018-2023",
   "Debut": "18y 203d",
   "Last": "24y 7d"
 },
 {
   "Cap": 83,
   "#": 11,
   "Player": "Sherman, Justin",
   "DOB": "26/01/1987",
   "HT": "183cm",
   "WT": "89kg",
   "Games (W-D-L)": "114 (48-3-63)",
   "Goals": 85,
   "Seasons": "2005-2010",
   "Debut": "18y 80d",
   "Last": "23y 214d"
 },
 {
   "Cap": 203,
   "#": 11,
   "Player": "McCarthy, Lincoln",
   "DOB": "22/10/1993",
   "HT": "176cm",
   "WT": "84kg",
   "Games (W-D-L)": "114 (78-0-36)",
   "Goals": 134,
   "Seasons": "2019-2023",
   "Debut": "25y 152d",
   "Last": "29y 343d"
 },
 {
   "Cap": 197,
   "#": 16,
   "Player": "Rayner, Cam",
   "DOB": "21/10/1999",
   "HT": "187cm",
   "WT": "90kg",
   "Games (W-D-L)": "113 (69-0-44)",
   "Goals": 104,
   "Seasons": "2018-2020, 2022-2023",
   "Debut": "18y 154d",
   "Last": "23y 344d"
 },
 {
   "Cap": 156,
   "#": 28,
   "Player": "Taylor, Lewis",
   "DOB": "17/02/1995",
   "HT": "175cm",
   "WT": "80kg",
   "Games (W-D-L)": "112 (26-0-86)",
   "Goals": 88,
   "Seasons": "2014-2019",
   "Debut": "19y 33d",
   "Last": "24y 111d"
 },
 {
   "Cap": 78,
   "#": 35,
   "Player": "Rischitelli, Michael",
   "DOB": "8/01/1986",
   "HT": "185cm",
   "WT": "84kg",
   "Games (W-D-L)": "111 (49-3-59)",
   "Goals": 47,
   "Seasons": "2004-2010",
   "Debut": "18y 198d",
   "Last": "24y 232d"
 },
 {
   "Cap": 204,
   "#": 9,
   "Player": "Neale, Lachie",
   "DOB": "24/05/1993",
   "HT": "177cm",
   "WT": "85kg",
   "Games (W-D-L)": "111 (75-0-36)",
   "Goals": 48,
   "Seasons": "2019-2023",
   "Debut": "25y 303d",
   "Last": "30y 129d"
 },
 {
   "Cap": 105,
   "#": 23,
   "Player": "Leuenberger, Matthew",
   "DOB": "7/06/1988",
   "HT": "203cm",
   "WT": "103kg",
   "Games (W-D-L)": "108 (35-1-72)",
   "Goals": 27,
   "Seasons": "2007-2015",
   "Debut": "19y 30d",
   "Last": "27y 55d"
 },
 {
   "Cap": 62,
   "#": 13,
   "Player": "Pike, Martin",
   "DOB": "14/11/1972",
   "HT": "189cm",
   "WT": "92kg",
   "Games (W-D-L)": "106 (74-1-31)",
   "Goals": 67,
   "Seasons": "2001-2005",
   "Debut": "28y 137d",
   "Last": "32y 195d"
 },
 {
   "Cap": 130,
   "#": 8,
   "Player": "Bewick, Rohan",
   "DOB": "10/10/1989",
   "HT": "184cm",
   "WT": "83kg",
   "Games (W-D-L)": "103 (31-0-72)",
   "Goals": 71,
   "Seasons": "2011-2018",
   "Debut": "21y 167d",
   "Last": "28y 186d"
 },
 {
   "Cap": 149,
   "#": 32,
   "Player": "Mayes, Sam",
   "DOB": "20/05/1994",
   "HT": "189cm",
   "WT": "88kg",
   "Games (W-D-L)": "101 (27-0-74)",
   "Goals": 26,
   "Seasons": "2013-2018",
   "Debut": "18y 328d",
   "Last": "24y 34d"
 },
 {
   "Cap": 95,
   "#": 32,
   "Player": "Stiller, Cheynee",
   "DOB": "3/05/1986",
   "HT": "187cm",
   "WT": "84kg",
   "Games (W-D-L)": "100 (38-3-59)",
   "Goals": 21,
   "Seasons": "2006-2012",
   "Debut": "19y 345d",
   "Last": "26y 65d"
 },
 {
   "Cap": 202,
   "#": 17,
   "Player": "Lyons, Jarryd",
   "DOB": "22/07/1992",
   "HT": "184cm",
   "WT": "84kg",
   "Games (W-D-L)": "99 (69-0-30)",
   "Goals": 37,
   "Seasons": "2019-2023",
   "Debut": "26y 244d",
   "Last": "31y 70d"
 },
 {
   "Cap": 201,
   "#": 37,
   "Player": "Starcevich, Brandon",
   "DOB": "24/07/1999",
   "HT": "188cm",
   "WT": "88kg",
   "Games (W-D-L)": "97 (67-0-30)",
   "Goals": 6,
   "Seasons": "2018-2023",
   "Debut": "19y 11d",
   "Last": "24y 68d"
 },
 {
   "Cap": 87,
   "#": 39,
   "Player": "Drummond, Josh",
   "DOB": "19/04/1983",
   "HT": "189cm",
   "WT": "88kg",
   "Games (W-D-L)": "94 (43-2-49)",
   "Goals": 35,
   "Seasons": "2005-2012",
   "Debut": "22y 25d",
   "Last": "29y 128d"
 },
 {
   "Cap": 108,
   "#": 31,
   "Player": "Polkinghorne, James",
   "DOB": "21/01/1989",
   "HT": "184cm",
   "WT": "87kg",
   "Games (W-D-L)": "94 (36-1-57)",
   "Goals": 53,
   "Seasons": "2008-2014",
   "Debut": "19y 97d",
   "Last": "25y 102d"
 },
 {
   "Cap": 44,
   "#": 43,
   "Player": "McDonald, Beau",
   "DOB": "3/11/1979",
   "HT": "203cm",
   "WT": "103kg",
   "Games (W-D-L)": "91 (58-1-32)",
   "Goals": 19,
   "Seasons": "1998-2003, 2006-2007",
   "Debut": "18y 167d",
   "Last": "27y 204d"
 },
 {
   "Cap": 90,
   "#": 1,
   "Player": "Clark, Mitch",
   "DOB": "19/10/1987",
   "HT": "200cm",
   "WT": "103kg",
   "Games (W-D-L)": "82 (31-2-49)",
   "Goals": 61,
   "Seasons": "2006-2011",
   "Debut": "18y 164d",
   "Last": "23y 305d"
 },
 {
   "Cap": 127,
   "#": 2,
   "Player": "Harwood, Ryan",
   "DOB": "7/08/1991",
   "HT": "184cm",
   "WT": "87kg",
   "Games (W-D-L)": "81 (26-0-55)",
   "Goals": 6,
   "Seasons": "2010-2017",
   "Debut": "18y 351d",
   "Last": "25y 314d"
 },
 {
   "Cap": 135,
   "#": 6,
   "Player": "Green, Josh",
   "DOB": "24/08/1992",
   "HT": "178cm",
   "WT": "77kg",
   "Games (W-D-L)": "81 (29-0-52)",
   "Goals": 107,
   "Seasons": "2011-2016",
   "Debut": "18y 270d",
   "Last": "23y 348d"
 },
 {
   "Cap": 77,
   "#": 26,
   "Player": "Macdonald, Joel",
   "DOB": "10/10/1984",
   "HT": "188cm",
   "WT": "88kg",
   "Games (W-D-L)": "80 (45-1-34)",
   "Goals": 6,
   "Seasons": "2004-2009",
   "Debut": "19y 233d",
   "Last": "24y 323d"
 },
 {
   "Cap": 10,
   "#": 41,
   "Player": "Kennedy, Matthew",
   "DOB": "4/02/1970",
   "HT": "191cm",
   "WT": "98kg",
   "Games (W-D-L)": "75 (35-1-39)",
   "Goals": 5,
   "Seasons": "1997-2001",
   "Debut": "27y 54d",
   "Last": "31y 230d"
 },
 {
   "Cap": 79,
   "#": 28,
   "Player": "Selwood, Troy",
   "DOB": "1/05/1984",
   "HT": "187cm",
   "WT": "85kg",
   "Games (W-D-L)": "75 (32-2-41)",
   "Goals": 11,
   "Seasons": "2005-2010",
   "Debut": "20y 327d",
   "Last": "26y 113d"
 },
 {
   "Cap": 160,
   "#": 18,
   "Player": "Robertson, Nick",
   "DOB": "3/06/1995",
   "HT": "191cm",
   "WT": "98kg",
   "Games (W-D-L)": "73 (13-0-60)",
   "Goals": 10,
   "Seasons": "2014-2019",
   "Debut": "18y 313d",
   "Last": "24y 103d"
 },
 {
   "Cap": 180,
   "#": 36,
   "Player": "Mathieson, Rhys",
   "DOB": "10/01/1997",
   "HT": "188cm",
   "WT": "87kg",
   "Games (W-D-L)": "72 (34-0-38)",
   "Goals": 29,
   "Seasons": "2016-2022",
   "Debut": "19y 133d",
   "Last": "25y 249d"
 },
 {
   "Cap": 209,
   "#": 4,
   "Player": "Ah Chee, Callum",
   "DOB": "9/10/1997",
   "HT": "182cm",
   "WT": "78kg",
   "Games (W-D-L)": "72 (55-0-17)",
   "Goals": 24,
   "Seasons": "2020-2023",
   "Debut": "22y 248d",
   "Last": "25y 356d"
 },
 {
   "Cap": 123,
   "#": 36,
   "Player": "Maguire, Matt",
   "DOB": "30/05/1984",
   "HT": "192cm",
   "WT": "101kg",
   "Games (W-D-L)": "71 (28-0-43)",
   "Goals": 2,
   "Seasons": "2010-2015",
   "Debut": "25y 301d",
   "Last": "30y 323d"
 },
 {
   "Cap": 217,
   "#": 3,
   "Player": "Daniher, Joe",
   "DOB": "4/03/1994",
   "HT": "200cm",
   "WT": "99kg",
   "Games (W-D-L)": "69 (47-0-22)",
   "Goals": 146,
   "Seasons": "2021-2023",
   "Debut": "27y 16d",
   "Last": "29y 210d"
 },
 {
   "Cap": 37,
   "#": 15,
   "Player": "Lawrence, Steven",
   "DOB": "19/05/1976",
   "HT": "177cm",
   "WT": "83kg",
   "Games (W-D-L)": "68 (34-2-32)",
   "Goals": 42,
   "Seasons": "1997-2000",
   "Debut": "21y 54d",
   "Last": "24y 92d"
 },
 {
   "Cap": 168,
   "#": 3,
   "Player": "Christensen, Allen",
   "DOB": "19/05/1991",
   "HT": "177cm",
   "WT": "80kg",
   "Games (W-D-L)": "68 (19-0-49)",
   "Goals": 58,
   "Seasons": "2015-2016, 2018-2019",
   "Debut": "23y 320d",
   "Last": "28y 118d"
 },
 {
   "Cap": 124,
   "#": 29,
   "Player": "Raines, Andrew",
   "DOB": "8/03/1986",
   "HT": "183cm",
   "WT": "82kg",
   "Games (W-D-L)": "67 (25-0-42)",
   "Goals": 14,
   "Seasons": "2010-2014",
   "Debut": "24y 19d",
   "Last": "28y 70d"
 },
 {
   "Cap": 158,
   "#": 26,
   "Player": "Cutler, Tom",
   "DOB": "20/02/1995",
   "HT": "192cm",
   "WT": "92kg",
   "Games (W-D-L)": "66 (18-0-48)",
   "Goals": 32,
   "Seasons": "2014-2019",
   "Debut": "19y 51d",
   "Last": "24y 80d"
 },
 {
   "Cap": 2,
   "#": 1,
   "Player": "Champion, Richard",
   "DOB": "14/04/1968",
   "HT": "186cm",
   "WT": "94kg",
   "Games (W-D-L)": "64 (30-1-33)",
   "Goals": 43,
   "Seasons": "1997-2000",
   "Debut": "28y 350d",
   "Last": "32y 72d"
 },
 {
   "Cap": 216,
   "#": 18,
   "Player": "Coleman, Keidean",
   "DOB": "31/03/2000",
   "HT": "183cm",
   "WT": "75kg",
   "Games (W-D-L)": "64 (43-0-21)",
   "Goals": 14,
   "Seasons": "2020-2023",
   "Debut": "20y 157d",
   "Last": "23y 183d"
 },
 {
   "Cap": 3,
   "#": 16,
   "Player": "Clarke, Matthew",
   "DOB": "18/09/1973",
   "HT": "200cm",
   "WT": "100kg",
   "Games (W-D-L)": "61 (26-1-34)",
   "Goals": 13,
   "Seasons": "1997-1999",
   "Debut": "23y 193d",
   "Last": "25y 364d"
 },
 {
   "Cap": 17,
   "#": 7,
   "Player": "Molloy, Jarrod",
   "DOB": "12/05/1976",
   "HT": "189cm",
   "WT": "99kg",
   "Games (W-D-L)": "61 (37-1-23)",
   "Goals": 104,
   "Seasons": "1997-2000",
   "Debut": "20y 322d",
   "Last": "24y 99d"
 },
 {
   "Cap": 192,
   "#": 29,
   "Player": "Witherden, Alex",
   "DOB": "10/09/1998",
   "HT": "188cm",
   "WT": "85kg",
   "Games (W-D-L)": "59 (26-0-33)",
   "Goals": 5,
   "Seasons": "2017-2020",
   "Debut": "18y 287d",
   "Last": "21y 348d"
 },
 {
   "Cap": 167,
   "#": 9,
   "Player": "Beams, Dayne",
   "DOB": "12/02/1990",
   "HT": "187cm",
   "WT": "88kg",
   "Games (W-D-L)": "58 (11-0-47)",
   "Goals": 49,
   "Seasons": "2015-2018",
   "Debut": "25y 51d",
   "Last": "28y 195d"
 },
 {
   "Cap": 57,
   "#": 34,
   "Player": "Shattock, Aaron",
   "DOB": "2/05/1980",
   "HT": "187cm",
   "WT": "87kg",
   "Games (W-D-L)": "57 (35-1-21)",
   "Goals": 15,
   "Seasons": "2000-2004",
   "Debut": "19y 342d",
   "Last": "24y 20d"
 },
 {
   "Cap": 136,
   "#": 41,
   "Player": "Golby, Mitch",
   "DOB": "3/10/1991",
   "HT": "184cm",
   "WT": "84kg",
   "Games (W-D-L)": "56 (21-0-35)",
   "Goals": 6,
   "Seasons": "2011-2015",
   "Debut": "19y 252d",
   "Last": "23y 233d"
 },
 {
   "Cap": 152,
   "#": 42,
   "Player": "Clarke, Justin",
   "DOB": "18/11/1993",
   "HT": "195cm",
   "WT": "93kg",
   "Games (W-D-L)": "56 (17-0-39)",
   "Goals": 1,
   "Seasons": "2013-2015",
   "Debut": "19y 161d",
   "Last": "21y 291d"
 },
 {
   "Cap": 151,
   "#": 22,
   "Player": "Paparone, Marco",
   "DOB": "3/09/1994",
   "HT": "194cm",
   "WT": "88kg",
   "Games (W-D-L)": "55 (12-0-43)",
   "Goals": 13,
   "Seasons": "2013-2017",
   "Debut": "18y 230d",
   "Last": "22y 287d"
 },
 {
   "Cap": 205,
   "#": 43,
   "Player": "Answerth, Noah",
   "DOB": "6/08/1999",
   "HT": "182cm",
   "WT": "82kg",
   "Games (W-D-L)": "55 (39-0-16)",
   "Goals": 2,
   "Seasons": "2019-2020, 2022-2023",
   "Debut": "19y 264d",
   "Last": "23y 280d"
 },
 {
   "Cap": 129,
   "#": 17,
   "Player": "Beams, Claye",
   "DOB": "1/09/1991",
   "HT": "182cm",
   "WT": "85kg",
   "Games (W-D-L)": "54 (13-0-41)",
   "Goals": 27,
   "Seasons": "2011-2017",
   "Debut": "19y 206d",
   "Last": "25y 359d"
 },
 {
   "Cap": 74,
   "#": 18,
   "Player": "Corrie, Anthony",
   "DOB": "22/06/1984",
   "HT": "186cm",
   "WT": "80kg",
   "Games (W-D-L)": "53 (23-0-30)",
   "Goals": 48,
   "Seasons": "2004-2008",
   "Debut": "19y 300d",
   "Last": "24y 69d"
 },
 {
   "Cap": 120,
   "#": 18,
   "Player": "Banfield, Todd",
   "DOB": "28/06/1990",
   "HT": "183cm",
   "WT": "83kg",
   "Games (W-D-L)": "53 (13-0-40)",
   "Goals": 57,
   "Seasons": "2010-2012",
   "Debut": "19y 272d",
   "Last": "22y 44d"
 },
 {
   "Cap": 51,
   "#": 1,
   "Player": "Headland, Des",
   "DOB": "21/01/1981",
   "HT": "186cm",
   "WT": "91kg",
   "Games (W-D-L)": "52 (40-0-12)",
   "Goals": 52,
   "Seasons": "1999-2002",
   "Debut": "18y 157d",
   "Last": "21y 250d"
 },
 {
   "Cap": 178,
   "#": 14,
   "Player": "Walker, Josh",
   "DOB": "12/11/1992",
   "HT": "197cm",
   "WT": "100kg",
   "Games (W-D-L)": "52 (18-0-34)",
   "Goals": 34,
   "Seasons": "2016-2019",
   "Debut": "23y 136d",
   "Last": "26y 257d"
 },
 {
   "Cap": 96,
   "#": 29,
   "Player": "Roe, Jason",
   "DOB": "13/03/1984",
   "HT": "192cm",
   "WT": "87kg",
   "Games (W-D-L)": "50 (23-1-26)",
   "Goals": 7,
   "Seasons": "2006-2009",
   "Debut": "22y 55d",
   "Last": "25y 176d"
 },
 {
   "Cap": 125,
   "#": 14,
   "Player": "Staker, Brent",
   "DOB": "23/05/1984",
   "HT": "196cm",
   "WT": "98kg",
   "Games (W-D-L)": "50 (16-0-34)",
   "Goals": 35,
   "Seasons": "2010-2011, 2013, 2015",
   "Debut": "25y 308d",
   "Last": "31y 63d"
 },
 {
   "Cap": 214,
   "#": 40,
   "Player": "Payne, Jack",
   "DOB": "15/10/1999",
   "HT": "197cm",
   "WT": "101kg",
   "Games (W-D-L)": "50 (32-0-18)",
   "Goals": 2,
   "Seasons": "2020-2023",
   "Debut": "20y 294d",
   "Last": "23y 329d"
 },
 {
   "Cap": 106,
   "#": 4,
   "Player": "Johnstone, Travis",
   "DOB": "17/07/1980",
   "HT": "184cm",
   "WT": "83kg",
   "Games (W-D-L)": "49 (22-0-27)",
   "Goals": 24,
   "Seasons": "2008-2010",
   "Debut": "27y 249d",
   "Last": "30y 29d"
 },
 {
   "Cap": 92,
   "#": 5,
   "Player": "Harding, Scott",
   "DOB": "19/06/1986",
   "HT": "181cm",
   "WT": "82kg",
   "Games (W-D-L)": "48 (26-3-19)",
   "Goals": 15,
   "Seasons": "2006-2009",
   "Debut": "19y 286d",
   "Last": "23y 78d"
 },
 {
   "Cap": 93,
   "#": 33,
   "Player": "Hooper, Rhan",
   "DOB": "9/01/1988",
   "HT": "177cm",
   "WT": "78kg",
   "Games (W-D-L)": "48 (23-1-24)",
   "Goals": 49,
   "Seasons": "2006-2009",
   "Debut": "18y 89d",
   "Last": "21y 245d"
 },
 {
   "Cap": 18,
   "#": 28,
   "Player": "Robbins, Ben",
   "DOB": "27/12/1976",
   "HT": "181cm",
   "WT": "77kg",
   "Games (W-D-L)": "47 (22-2-23)",
   "Goals": 13,
   "Seasons": "1997-2001",
   "Debut": "20y 93d",
   "Last": "24y 206d"
 },
 {
   "Cap": 24,
   "#": 18,
   "Player": "Lambert, Craig",
   "DOB": "5/10/1968",
   "HT": "178cm",
   "WT": "84kg",
   "Games (W-D-L)": "47 (25-1-21)",
   "Goals": 8,
   "Seasons": "1997-2000",
   "Debut": "28y 183d",
   "Last": "31y 278d"
 },
 {
   "Cap": 67,
   "#": 25,
   "Player": "McLaren, Dylan",
   "DOB": "8/05/1982",
   "HT": "196cm",
   "WT": "98kg",
   "Games (W-D-L)": "46 (31-0-15)",
   "Goals": 6,
   "Seasons": "2001-2005",
   "Debut": "19y 103d",
   "Last": "23y 111d"
 },
 {
   "Cap": 207,
   "#": 24,
   "Player": "Adams, Marcus",
   "DOB": "30/06/1993",
   "HT": "192cm",
   "WT": "93kg",
   "Games (W-D-L)": "46 (32-0-14)",
   "Goals": 1,
   "Seasons": "2019-2022",
   "Debut": "26y 7d",
   "Last": "29y 38d"
 },
 {
   "Cap": 4,
   "#": 14,
   "Player": "Dickfos, Danny",
   "DOB": "30/09/1970",
   "HT": "188cm",
   "WT": "94kg",
   "Games (W-D-L)": "43 (17-2-24)",
   "Goals": null,
   "Seasons": "1997-1999",
   "Debut": "26y 181d",
   "Last": "28y 312d"
 },
 {
   "Cap": 115,
   "#": 3,
   "Player": "Sheldon, Sam",
   "DOB": "8/03/1989",
   "HT": "184cm",
   "WT": "80kg",
   "Games (W-D-L)": "43 (19-1-23)",
   "Goals": 11,
   "Seasons": "2009-2012",
   "Debut": "20y 55d",
   "Last": "23y 51d"
 },
 {
   "Cap": 175,
   "#": 4,
   "Player": "Bastinac, Ryan",
   "DOB": "22/06/1991",
   "HT": "186cm",
   "WT": "82kg",
   "Games (W-D-L)": "43 (11-0-32)",
   "Goals": 27,
   "Seasons": "2016-2019",
   "Debut": "24y 279d",
   "Last": "27y 288d"
 },
 {
   "Cap": 63,
   "#": 14,
   "Player": "Hadley, Richard",
   "DOB": "29/03/1983",
   "HT": "190cm",
   "WT": "90kg",
   "Games (W-D-L)": "41 (22-2-17)",
   "Goals": 10,
   "Seasons": "2001, 2003-2004, 2007",
   "Debut": "18y 16d",
   "Last": "24y 156d"
 },
 {
   "Cap": 196,
   "#": 2,
   "Player": "Hodge, Luke",
   "DOB": "15/06/1984",
   "HT": "185cm",
   "WT": "92kg",
   "Games (W-D-L)": "41 (18-0-23)",
   "Goals": 1,
   "Seasons": "2018-2019",
   "Debut": "33y 282d",
   "Last": "35y 91d"
 },
 {
   "Cap": 208,
   "#": 2,
   "Player": "Robertson, Deven",
   "DOB": "30/06/2001",
   "HT": "182cm",
   "WT": "80kg",
   "Games (W-D-L)": "41 (27-0-14)",
   "Goals": 10,
   "Seasons": "2020-2023",
   "Debut": "18y 266d",
   "Last": "22y 92d"
 },
 {
   "Cap": 48,
   "#": 31,
   "Player": "Heuskes, Adam",
   "DOB": "20/03/1976",
   "HT": "190cm",
   "WT": "93kg",
   "Games (W-D-L)": "39 (24-0-15)",
   "Goals": 5,
   "Seasons": "1999-2000",
   "Debut": "23y 7d",
   "Last": "24y 131d"
 },
 {
   "Cap": 211,
   "#": 14,
   "Player": "Birchall, Grant",
   "DOB": "28/01/1988",
   "HT": "193cm",
   "WT": "89kg",
   "Games (W-D-L)": "39 (28-0-11)",
   "Goals": 2,
   "Seasons": "2020-2021",
   "Debut": "32y 137d",
   "Last": "33y 219d"
 },
 {
   "Cap": 28,
   "#": 13,
   "Player": "Voss, Brett",
   "DOB": "22/02/1978",
   "HT": "181cm",
   "WT": "83kg",
   "Games (W-D-L)": "35 (19-1-15)",
   "Goals": 11,
   "Seasons": "1997-2000",
   "Debut": "19y 64d",
   "Last": "22y 179d"
 },
 {
   "Cap": 219,
   "#": 20,
   "Player": "Prior, Jaxon",
   "DOB": "4/06/2001",
   "HT": "188cm",
   "WT": "79kg",
   "Games (W-D-L)": "35 (26-0-9)",
   "Goals": 11,
   "Seasons": "2021-2023",
   "Debut": "19y 295d",
   "Last": "22y 69d"
 },
 {
   "Cap": 14,
   "#": 42,
   "Player": "Lynch, Tristan",
   "DOB": "22/08/1973",
   "HT": "188cm",
   "WT": "80kg",
   "Games (W-D-L)": "34 (12-1-21)",
   "Goals": 7,
   "Seasons": "1997-1998",
   "Debut": "23y 220d",
   "Last": "25y 7d"
 },
 {
   "Cap": 70,
   "#": 1,
   "Player": "Caracella, Blake",
   "DOB": "15/03/1977",
   "HT": "186cm",
   "WT": "85kg",
   "Games (W-D-L)": "34 (23-1-10)",
   "Goals": 33,
   "Seasons": "2003-2004",
   "Debut": "26y 14d",
   "Last": "27y 194d"
 },
 {
   "Cap": 85,
   "#": 10,
   "Player": "Moody, Matthew",
   "DOB": "23/09/1985",
   "HT": "187cm",
   "WT": "85kg",
   "Games (W-D-L)": "34 (12-1-21)",
   "Goals": 14,
   "Seasons": "2005-2008",
   "Debut": "19y 219d",
   "Last": "22y 335d"
 },
 {
   "Cap": 109,
   "#": 12,
   "Player": "Hawksley, James",
   "DOB": "5/02/1989",
   "HT": "187cm",
   "WT": "84kg",
   "Games (W-D-L)": "32 (11-1-20)",
   "Goals": 6,
   "Seasons": "2008-2012",
   "Debut": "19y 124d",
   "Last": "23y 210d"
 },
 {
   "Cap": 154,
   "#": 4,
   "Player": "Aish, James",
   "DOB": "8/11/1995",
   "HT": "183cm",
   "WT": "80kg",
   "Games (W-D-L)": "32 (8-0-24)",
   "Goals": 8,
   "Seasons": "2014-2015",
   "Debut": "18y 134d",
   "Last": "19y 259d"
 },
 {
   "Cap": 179,
   "#": 1,
   "Player": "Keays, Ben",
   "DOB": "23/02/1997",
   "HT": "185cm",
   "WT": "89kg",
   "Games (W-D-L)": "30 (6-0-24)",
   "Goals": 11,
   "Seasons": "2016-2019",
   "Debut": "19y 68d",
   "Last": "22y 141d"
 },
 {
   "Cap": 52,
   "#": 26,
   "Player": "Bolton, Craig",
   "DOB": "31/05/1980",
   "HT": "190cm",
   "WT": "87kg",
   "Games (W-D-L)": "29 (17-0-12)",
   "Goals": 10,
   "Seasons": "2000-2002",
   "Debut": "19y 287d",
   "Last": "22y 51d"
 },
 {
   "Cap": 100,
   "#": 46,
   "Player": "Begley, Colm",
   "DOB": "31/08/1986",
   "HT": "188cm",
   "WT": "83kg",
   "Games (W-D-L)": "29 (10-2-17)",
   "Goals": 7,
   "Seasons": "2006-2008",
   "Debut": "19y 354d",
   "Last": "21y 351d"
 },
 {
   "Cap": 102,
   "#": 2,
   "Player": "Proud, Albert",
   "DOB": "6/09/1988",
   "HT": "180cm",
   "WT": "83kg",
   "Games (W-D-L)": "29 (14-0-15)",
   "Goals": 10,
   "Seasons": "2007-2010",
   "Debut": "18y 284d",
   "Last": "21y 356d"
 },
 {
   "Cap": 226,
   "#": 44,
   "Player": "Wilmot, Darcy",
   "DOB": "31/12/2003",
   "HT": "183cm",
   "WT": "75kg",
   "Games (W-D-L)": "29 (21-0-8)",
   "Goals": 6,
   "Seasons": "2022-2023",
   "Debut": "18y 244d",
   "Last": "19y 273d"
 },
 {
   "Cap": 91,
   "#": 4,
   "Player": "Fixter, Ben",
   "DOB": "23/06/1981",
   "HT": "180cm",
   "WT": "84kg",
   "Games (W-D-L)": "27 (10-0-17)",
   "Goals": 3,
   "Seasons": "2006-2007",
   "Debut": "24y 282d",
   "Last": "25y 337d"
 },
 {
   "Cap": 110,
   "#": 22,
   "Player": "Collier, Tom",
   "DOB": "25/03/1989",
   "HT": "192cm",
   "WT": "84kg",
   "Games (W-D-L)": "27 (8-0-19)",
   "Goals": 4,
   "Seasons": "2008-2011",
   "Debut": "19y 88d",
   "Last": "22y 85d"
 },
 {
   "Cap": 144,
   "#": 26,
   "Player": "Yeo, Elliot",
   "DOB": "1/10/1993",
   "HT": "190cm",
   "WT": "89kg",
   "Games (W-D-L)": "27 (11-0-16)",
   "Goals": 1,
   "Seasons": "2012-2013",
   "Debut": "18y 239d",
   "Last": "19y 334d"
 },
 {
   "Cap": 155,
   "#": 33,
   "Player": "Close, Michael",
   "DOB": "30/07/1994",
   "HT": "197cm",
   "WT": "98kg",
   "Games (W-D-L)": "27 (7-0-20)",
   "Goals": 24,
   "Seasons": "2014-2017",
   "Debut": "19y 235d",
   "Last": "23y 27d"
 },
 {
   "Cap": 177,
   "#": 23,
   "Player": "Schache, Josh",
   "DOB": "21/08/1997",
   "HT": "199cm",
   "WT": "94kg",
   "Games (W-D-L)": "27 (3-0-24)",
   "Goals": 25,
   "Seasons": "2016-2017",
   "Debut": "18y 219d",
   "Last": "19y 349d"
 },
 {
   "Cap": 230,
   "#": 26,
   "Player": "McKenna, Conor",
   "DOB": "28/03/1996",
   "HT": "184cm",
   "WT": "88kg",
   "Games (W-D-L)": "26 (19-0-7)",
   "Goals": 7,
   "Seasons": "2023",
   "Debut": "26y 355d",
   "Last": "27y 186d"
 },
 {
   "Cap": 43,
   "#": 24,
   "Player": "Picken, Marcus",
   "DOB": "9/10/1979",
   "HT": "186cm",
   "WT": "86kg",
   "Games (W-D-L)": "25 (10-0-15)",
   "Goals": 9,
   "Seasons": "1998-2001",
   "Debut": "18y 186d",
   "Last": "21y 229d"
 },
 {
   "Cap": 117,
   "#": 44,
   "Player": "Cornelius, Aaron",
   "DOB": "29/05/1990",
   "HT": "192cm",
   "WT": "88kg",
   "Games (W-D-L)": "25 (6-0-19)",
   "Goals": 35,
   "Seasons": "2009-2013",
   "Debut": "18y 360d",
   "Last": "22y 341d"
 },
 {
   "Cap": 222,
   "#": 32,
   "Player": "Fort, Darcy",
   "DOB": "6/08/1993",
   "HT": "204cm",
   "WT": "99kg",
   "Games (W-D-L)": "25 (19-0-6)",
   "Goals": 10,
   "Seasons": "2022-2023",
   "Debut": "28y 225d",
   "Last": "30y"
 },
 {
   "Cap": 19,
   "#": 38,
   "Player": "Scott, Dion",
   "DOB": "1/04/1970",
   "HT": "190cm",
   "WT": "105kg",
   "Games (W-D-L)": "24 (7-1-16)",
   "Goals": 22,
   "Seasons": "1997-1999",
   "Debut": "26y 363d",
   "Last": "29y 9d"
 },
 {
   "Cap": 22,
   "#": 34,
   "Player": "Bamford, Scott",
   "DOB": "23/06/1974",
   "HT": "183cm",
   "WT": "68kg",
   "Games (W-D-L)": "24 (6-2-16)",
   "Goals": 17,
   "Seasons": "1997-1998",
   "Debut": "22y 287d",
   "Last": "24y 67d"
 },
 {
   "Cap": 228,
   "#": 5,
   "Player": "Dunkley, Josh",
   "DOB": "9/01/1997",
   "HT": "190cm",
   "WT": "88kg",
   "Games (W-D-L)": "24 (18-0-6)",
   "Goals": 2,
   "Seasons": "2023",
   "Debut": "26y 68d",
   "Last": "26y 264d"
 },
 {
   "Cap": 138,
   "#": 40,
   "Player": "McKeever, Niall",
   "DOB": "16/02/1989",
   "HT": "196cm",
   "WT": "95kg",
   "Games (W-D-L)": "22 (7-0-15)",
   "Goals": 2,
   "Seasons": "2011-2013",
   "Debut": "22y 129d",
   "Last": "24y 119d"
 },
 {
   "Cap": 187,
   "#": 43,
   "Player": "Barrett, Jake",
   "DOB": "8/11/1995",
   "HT": "184cm",
   "WT": "83kg",
   "Games (W-D-L)": "22 (8-0-14)",
   "Goals": 19,
   "Seasons": "2017-2018",
   "Debut": "21y 137d",
   "Last": "22y 262d"
 },
 {
   "Cap": 5,
   "#": 6,
   "Player": "Fletcher, Adrian",
   "DOB": "10/10/1969",
   "HT": "178cm",
   "WT": "84kg",
   "Games (W-D-L)": "21 (8-1-12)",
   "Goals": 4,
   "Seasons": "1997",
   "Debut": "27y 171d",
   "Last": "27y 332d"
 },
 {
   "Cap": 137,
   "#": 28,
   "Player": "Karnezis, Patrick",
   "DOB": "23/04/1992",
   "HT": "191cm",
   "WT": "88kg",
   "Games (W-D-L)": "21 (3-0-18)",
   "Goals": 24,
   "Seasons": "2011-2013",
   "Debut": "19y 56d",
   "Last": "21y 38d"
 },
 {
   "Cap": 148,
   "#": 3,
   "Player": "Moloney, Brent",
   "DOB": "28/01/1984",
   "HT": "181cm",
   "WT": "88kg",
   "Games (W-D-L)": "21 (5-0-16)",
   "Goals": 9,
   "Seasons": "2013-2014",
   "Debut": "29y 61d",
   "Last": "30y 79d"
 },
 {
   "Cap": 176,
   "#": 7,
   "Player": "Bell, Tom",
   "DOB": "13/06/1991",
   "HT": "188cm",
   "WT": "102kg",
   "Games (W-D-L)": "21 (2-0-19)",
   "Goals": 20,
   "Seasons": "2016-2018",
   "Debut": "24y 288d",
   "Last": "26y 284d"
 },
 {
   "Cap": 210,
   "#": 13,
   "Player": "Berry, Tom",
   "DOB": "1/05/2001",
   "HT": "185cm",
   "WT": "76kg",
   "Games (W-D-L)": "20 (15-0-5)",
   "Goals": 3,
   "Seasons": "2020-2022",
   "Debut": "19y 43d",
   "Last": "21y 53d"
 },
 {
   "Cap": 23,
   "#": 25,
   "Player": "Bews, Andrew",
   "DOB": "19/07/1964",
   "HT": "175cm",
   "WT": "79kg",
   "Games (W-D-L)": "19 (9-0-10)",
   "Goals": null,
   "Seasons": "1997-1998",
   "Debut": "32y 261d",
   "Last": "34y 41d"
 },
 {
   "Cap": 41,
   "#": 21,
   "Player": "OBree, Shane",
   "DOB": "15/03/1979",
   "HT": "182cm",
   "WT": "81kg",
   "Games (W-D-L)": "19 (9-0-10)",
   "Goals": 3,
   "Seasons": "1998-1999",
   "Debut": "19y 20d",
   "Last": "20y 186d"
 },
 {
   "Cap": 215,
   "#": 21,
   "Player": "Fullarton, Tom",
   "DOB": "23/02/1999",
   "HT": "199cm",
   "WT": "92kg",
   "Games (W-D-L)": "19 (9-0-10)",
   "Goals": 6,
   "Seasons": "2020-2022",
   "Debut": "21y 182d",
   "Last": "23y 198d"
 },
 {
   "Cap": 121,
   "#": 33,
   "Player": "Buchanan, Amon",
   "DOB": "10/10/1982",
   "HT": "179cm",
   "WT": "83kg",
   "Games (W-D-L)": "18 (3-0-15)",
   "Goals": 9,
   "Seasons": "2010-2012",
   "Debut": "27y 168d",
   "Last": "29y 328d"
 },
 {
   "Cap": 140,
   "#": 22,
   "Player": "Hudson, Ben",
   "DOB": "24/02/1979",
   "HT": "196cm",
   "WT": "105kg",
   "Games (W-D-L)": "18 (9-0-9)",
   "Goals": 3,
   "Seasons": "2012",
   "Debut": "33y 36d",
   "Last": "33y 191d"
 },
 {
   "Cap": 142,
   "#": 47,
   "Player": "Crisp, Jack",
   "DOB": "2/10/1993",
   "HT": "190cm",
   "WT": "90kg",
   "Games (W-D-L)": "18 (7-0-11)",
   "Goals": 10,
   "Seasons": "2012-2014",
   "Debut": "18y 202d",
   "Last": "20y 332d"
 },
 {
   "Cap": 146,
   "#": 19,
   "Player": "Lisle, Jordan",
   "DOB": "12/07/1990",
   "HT": "196cm",
   "WT": "95kg",
   "Games (W-D-L)": "18 (6-0-12)",
   "Goals": 15,
   "Seasons": "2012-2014",
   "Debut": "22y 23d",
   "Last": "23y 309d"
 },
 {
   "Cap": 172,
   "#": 24,
   "Player": "Dawson, Liam",
   "DOB": "23/01/1996",
   "HT": "188cm",
   "WT": "84kg",
   "Games (W-D-L)": "18 (4-0-14)",
   "Goals": 6,
   "Seasons": "2015-2017",
   "Debut": "19y 121d",
   "Last": "21y 89d"
 },
 {
   "Cap": 227,
   "#": 8,
   "Player": "Ashcroft, Will",
   "DOB": "6/05/2004",
   "HT": "182cm",
   "WT": "78kg",
   "Games (W-D-L)": "18 (13-0-5)",
   "Goals": 8,
   "Seasons": "2023",
   "Debut": "18y 316d",
   "Last": "19y 77d"
 },
 {
   "Cap": 38,
   "#": 17,
   "Player": "Bartlett, Trent",
   "DOB": "26/11/1976",
   "HT": "189cm",
   "WT": "95kg",
   "Games (W-D-L)": "17 (5-1-11)",
   "Goals": 7,
   "Seasons": "1998-1999",
   "Debut": "21y 122d",
   "Last": "22y 171d"
 },
 {
   "Cap": 122,
   "#": 5,
   "Player": "Fevola, Brendan",
   "DOB": "20/01/1981",
   "HT": "191cm",
   "WT": "100kg",
   "Games (W-D-L)": "17 (5-0-12)",
   "Goals": 48,
   "Seasons": "2010",
   "Debut": "29y 66d",
   "Last": "29y 192d"
 },
 {
   "Cap": 126,
   "#": 34,
   "Player": "OBrien, Jesse",
   "DOB": "13/02/1991",
   "HT": "184cm",
   "WT": "71kg",
   "Games (W-D-L)": "17 (4-0-13)",
   "Goals": 4,
   "Seasons": "2010-2013",
   "Debut": "19y 138d",
   "Last": "22y 178d"
 },
 {
   "Cap": 229,
   "#": 19,
   "Player": "Gunston, Jack",
   "DOB": "16/10/1991",
   "HT": "193cm",
   "WT": "87kg",
   "Games (W-D-L)": "17 (11-0-6)",
   "Goals": 22,
   "Seasons": "2023",
   "Debut": "31y 153d",
   "Last": "31y 300d"
 },
 {
   "Cap": 84,
   "#": 31,
   "Player": "Wood, Cameron",
   "DOB": "4/03/1987",
   "HT": "204cm",
   "WT": "107kg",
   "Games (W-D-L)": "16 (3-0-13)",
   "Goals": null,
   "Seasons": "2005-2007",
   "Debut": "18y 51d",
   "Last": "20y 181d"
 },
 {
   "Cap": 94,
   "#": 25,
   "Player": "Mills, Wayde",
   "DOB": "29/08/1987",
   "HT": "196cm",
   "WT": "88kg",
   "Games (W-D-L)": "16 (8-1-7)",
   "Goals": 3,
   "Seasons": "2006-2008",
   "Debut": "18y 222d",
   "Last": "20y 227d"
 },
 {
   "Cap": 133,
   "#": 4,
   "Player": "Polec, Jared",
   "DOB": "12/10/1992",
   "HT": "187cm",
   "WT": "84kg",
   "Games (W-D-L)": "16 (7-0-9)",
   "Goals": 9,
   "Seasons": "2011-2013",
   "Debut": "18y 180d",
   "Last": "20y 183d"
 },
 {
   "Cap": 157,
   "#": 13,
   "Player": "West, Trent",
   "DOB": "17/10/1987",
   "HT": "199cm",
   "WT": "103kg",
   "Games (W-D-L)": "16 (3-0-13)",
   "Goals": 5,
   "Seasons": "2014-2016",
   "Debut": "26y 156d",
   "Last": "28y 238d"
 },
 {
   "Cap": 185,
   "#": 44,
   "Player": "Smith, Archie",
   "DOB": "19/07/1995",
   "HT": "201cm",
   "WT": "102kg",
   "Games (W-D-L)": "16 (9-0-7)",
   "Goals": 4,
   "Seasons": "2016-2017, 2019-2020",
   "Debut": "21y 11d",
   "Last": "25y 56d"
 },
 {
   "Cap": 35,
   "#": 9,
   "Player": "Boyd, Brad",
   "DOB": "10/08/1971",
   "HT": "186cm",
   "WT": "86kg",
   "Games (W-D-L)": "15 (7-0-8)",
   "Goals": 8,
   "Seasons": "1997-1999",
   "Debut": "25y 288d",
   "Last": "27y 279d"
 },
 {
   "Cap": 107,
   "#": 14,
   "Player": "Henderson, Lachie",
   "DOB": "14/12/1989",
   "HT": "196cm",
   "WT": "98kg",
   "Games (W-D-L)": "15 (8-0-7)",
   "Goals": 3,
   "Seasons": "2008-2009",
   "Debut": "18y 105d",
   "Last": "19y 258d"
 },
 {
   "Cap": 111,
   "#": 34,
   "Player": "Dalziell, Bradd",
   "DOB": "15/03/1987",
   "HT": "184cm",
   "WT": "82kg",
   "Games (W-D-L)": "15 (6-0-9)",
   "Goals": 4,
   "Seasons": "2008-2009",
   "Debut": "21y 126d",
   "Last": "22y 139d"
 },
 {
   "Cap": 116,
   "#": 37,
   "Player": "Austin, Matt",
   "DOB": "30/03/1989",
   "HT": "187cm",
   "WT": "75kg",
   "Games (W-D-L)": "15 (8-0-7)",
   "Goals": 2,
   "Seasons": "2009-2011",
   "Debut": "20y 47d",
   "Last": "22y 74d"
 },
 {
   "Cap": 221,
   "#": 12,
   "Player": "Cockatoo, Nakia",
   "DOB": "23/10/1996",
   "HT": "186cm",
   "WT": "90kg",
   "Games (W-D-L)": "15 (9-0-6)",
   "Goals": 7,
   "Seasons": "2021-2022",
   "Debut": "24y 274d",
   "Last": "25y 281d"
 },
 {
   "Cap": 165,
   "#": 34,
   "Player": "Freeman, Jonathan",
   "DOB": "27/04/1994",
   "HT": "198cm",
   "WT": "96kg",
   "Games (W-D-L)": "14 (3-0-11)",
   "Goals": 16,
   "Seasons": "2014-2016",
   "Debut": "20y 105d",
   "Last": "22y 38d"
 },
 {
   "Cap": 232,
   "#": 28,
   "Player": "Fletcher, Jaspa",
   "DOB": "24/02/2004",
   "HT": "183cm",
   "WT": "76kg",
   "Games (W-D-L)": "14 (11-0-3)",
   "Goals": 8,
   "Seasons": "2023",
   "Debut": "19y 112d",
   "Last": "19y 218d"
 },
 {
   "Cap": 58,
   "#": 21,
   "Player": "Cupido, Damian",
   "DOB": "11/03/1982",
   "HT": "184cm",
   "WT": "90kg",
   "Games (W-D-L)": "13 (7-0-6)",
   "Goals": 16,
   "Seasons": "2000-2001",
   "Debut": "18y 71d",
   "Last": "19y 63d"
 },
 {
   "Cap": 59,
   "#": 45,
   "Player": "Knobel, Trent",
   "DOB": "23/05/1980",
   "HT": "204cm",
   "WT": "106kg",
   "Games (W-D-L)": "13 (9-0-4)",
   "Goals": null,
   "Seasons": "2000-2001",
   "Debut": "20y 17d",
   "Last": "20y 361d"
 },
 {
   "Cap": 150,
   "#": 1,
   "Player": "Docherty, Sam",
   "DOB": "17/10/1993",
   "HT": "187cm",
   "WT": "87kg",
   "Games (W-D-L)": "13 (6-0-7)",
   "Goals": 1,
   "Seasons": "2013",
   "Debut": "19y 186d",
   "Last": "19y 312d"
 },
 {
   "Cap": 163,
   "#": 47,
   "Player": "OBrien, Zac",
   "DOB": "27/10/1990",
   "HT": "183cm",
   "WT": "78kg",
   "Games (W-D-L)": "13 (4-0-9)",
   "Goals": 1,
   "Seasons": "2014-2015",
   "Debut": "23y 216d",
   "Last": "24y 313d"
 },
 {
   "Cap": 191,
   "#": 20,
   "Player": "Cox, Cedric",
   "DOB": "19/08/1997",
   "HT": "181cm",
   "WT": "79kg",
   "Games (W-D-L)": "13 (3-0-10)",
   "Goals": 3,
   "Seasons": "2017-2019",
   "Debut": "19y 240d",
   "Last": "22y 6d"
 },
 {
   "Cap": 220,
   "#": 42,
   "Player": "Madden, James",
   "DOB": "15/11/1999",
   "HT": "186cm",
   "WT": "85kg",
   "Games (W-D-L)": "13 (8-0-5)",
   "Goals": 1,
   "Seasons": "2021-2023",
   "Debut": "21y 167d",
   "Last": "23y 235d"
 },
 {
   "Cap": 36,
   "#": 35,
   "Player": "Trask, Nick",
   "DOB": "6/02/1978",
   "HT": "175cm",
   "WT": "76kg",
   "Games (W-D-L)": "12 (4-0-8)",
   "Goals": 3,
   "Seasons": "1997-1998",
   "Debut": "19y 115d",
   "Last": "20y 170d"
 },
 {
   "Cap": 183,
   "#": 40,
   "Player": "Hammelmann, Matthew",
   "DOB": "8/03/1996",
   "HT": "197cm",
   "WT": "88kg",
   "Games (W-D-L)": "12 (2-0-10)",
   "Goals": 2,
   "Seasons": "2016-2017",
   "Debut": "20y 109d",
   "Last": "21y 122d"
 },
 {
   "Cap": 6,
   "#": 8,
   "Player": "Gowers, Andrew",
   "DOB": "11/04/1969",
   "HT": "191cm",
   "WT": "85kg",
   "Games (W-D-L)": "11 (3-1-7)",
   "Goals": 2,
   "Seasons": "1997-1999",
   "Debut": "27y 353d",
   "Last": "30y 97d"
 },
 {
   "Cap": 27,
   "#": 5,
   "Player": "Chapman, Nathan",
   "DOB": "7/05/1975",
   "HT": "189cm",
   "WT": "83kg",
   "Games (W-D-L)": "11 (3-1-7)",
   "Goals": 1,
   "Seasons": "1997",
   "Debut": "21y 348d",
   "Last": "22y 123d"
 },
 {
   "Cap": 134,
   "#": 37,
   "Player": "Retzlaff, Bryce",
   "DOB": "29/06/1991",
   "HT": "195cm",
   "WT": "95kg",
   "Games (W-D-L)": "11 (3-0-8)",
   "Goals": 6,
   "Seasons": "2011",
   "Debut": "19y 312d",
   "Last": "20y 66d"
 },
 {
   "Cap": 54,
   "#": 17,
   "Player": "Martin, Michael",
   "DOB": "25/02/1977",
   "HT": "182cm",
   "WT": "86kg",
   "Games (W-D-L)": "10 (4-0-6)",
   "Goals": null,
   "Seasons": "2000",
   "Debut": "23y 23d",
   "Last": "23y 92d"
 },
 {
   "Cap": 159,
   "#": 39,
   "Player": "Paine, Jackson",
   "DOB": "21/06/1993",
   "HT": "192cm",
   "WT": "95kg",
   "Games (W-D-L)": "10 (1-0-9)",
   "Goals": 3,
   "Seasons": "2014, 2016",
   "Debut": "20y 295d",
   "Last": "23y 61d"
 },
 {
   "Cap": 193,
   "#": 37,
   "Player": "Allison, Jacob",
   "DOB": "16/04/1998",
   "HT": "193cm",
   "WT": "82kg",
   "Games (W-D-L)": "10 (2-0-8)",
   "Goals": 2,
   "Seasons": "2017-2019",
   "Debut": "19y 105d",
   "Last": "21y 67d"
 },
 {
   "Cap": 218,
   "#": 22,
   "Player": "Sharp, Harry",
   "DOB": "17/12/2002",
   "HT": "183cm",
   "WT": "69kg",
   "Games (W-D-L)": "10 (7-0-3)",
   "Goals": 2,
   "Seasons": "2021-2023",
   "Debut": "18y 93d",
   "Last": "20y 154d"
 },
 {
   "Cap": 45,
   "#": 19,
   "Player": "Hilton, Rory",
   "DOB": "15/04/1979",
   "HT": "186cm",
   "WT": "92kg",
   "Games (W-D-L)": "9 (3-0-6)",
   "Goals": 3,
   "Seasons": "1998",
   "Debut": "19y 16d",
   "Last": "19y 102d"
 },
 {
   "Cap": 49,
   "#": 48,
   "Player": "Calthorpe, David",
   "DOB": "17/08/1973",
   "HT": "179cm",
   "WT": "92kg",
   "Games (W-D-L)": "9 (6-0-3)",
   "Goals": 2,
   "Seasons": "1999",
   "Debut": "25y 236d",
   "Last": "25y 327d"
 },
 {
   "Cap": 141,
   "#": 5,
   "Player": "Longer, Billy",
   "DOB": "12/05/1993",
   "HT": "202cm",
   "WT": "105kg",
   "Games (W-D-L)": "9 (2-0-7)",
   "Goals": null,
   "Seasons": "2012-2013",
   "Debut": "18y 338d",
   "Last": "20y 19d"
 },
 {
   "Cap": 212,
   "#": 28,
   "Player": "Ellis-Yolmen, Cam",
   "DOB": "28/01/1993",
   "HT": "190cm",
   "WT": "97kg",
   "Games (W-D-L)": "9 (7-0-2)",
   "Goals": 3,
   "Seasons": "2020",
   "Debut": "27y 144d",
   "Last": "27y 263d"
 },
 {
   "Cap": 29,
   "#": 26,
   "Player": "Barker, John",
   "DOB": "19/02/1975",
   "HT": "194cm",
   "WT": "93kg",
   "Games (W-D-L)": "8 (1-1-6)",
   "Goals": 1,
   "Seasons": "1997",
   "Debut": "22y 73d",
   "Last": "22y 185d"
 },
 {
   "Cap": 98,
   "#": 41,
   "Player": "Pask, Martin",
   "DOB": "2/01/1985",
   "HT": "191cm",
   "WT": "97kg",
   "Games (W-D-L)": "8 (2-0-6)",
   "Goals": 4,
   "Seasons": "2006",
   "Debut": "21y 159d",
   "Last": "21y 243d"
 },
 {
   "Cap": 181,
   "#": 16,
   "Player": "Jansen, Jarrad",
   "DOB": "2/05/1995",
   "HT": "192cm",
   "WT": "94kg",
   "Games (W-D-L)": "8 (1-0-7)",
   "Goals": 4,
   "Seasons": "2016-2017",
   "Debut": "21y 33d",
   "Last": "22y 89d"
 },
 {
   "Cap": 223,
   "#": 1,
   "Player": "Lohmann, Kai",
   "DOB": "6/05/2003",
   "HT": "185cm",
   "WT": "77kg",
   "Games (W-D-L)": "8 (7-0-1)",
   "Goals": 1,
   "Seasons": "2022-2023",
   "Debut": "18y 343d",
   "Last": "20y 112d"
 },
 {
   "Cap": 15,
   "#": 7,
   "Player": "McIvor, Scott",
   "DOB": "9/08/1966",
   "HT": "191cm",
   "WT": "87kg",
   "Games (W-D-L)": "7 (2-0-5)",
   "Goals": 4,
   "Seasons": "1997",
   "Debut": "30y 233d",
   "Last": "30y 364d"
 },
 {
   "Cap": 50,
   "#": 25,
   "Player": "McKinnon, Martin",
   "DOB": "5/07/1975",
   "HT": "189cm",
   "WT": "94kg",
   "Games (W-D-L)": "7 (4-0-3)",
   "Goals": 5,
   "Seasons": "1999-2000",
   "Debut": "23y 300d",
   "Last": "25y 4d"
 },
 {
   "Cap": 162,
   "#": 1,
   "Player": "McGuane, Luke",
   "DOB": "12/02/1987",
   "HT": "192cm",
   "WT": "90kg",
   "Games (W-D-L)": "7 (2-0-5)",
   "Goals": 7,
   "Seasons": "2014-2015",
   "Debut": "27y 64d",
   "Last": "28y 198d"
 },
 {
   "Cap": 174,
   "#": 46,
   "Player": "Evans, Billy",
   "DOB": "19/10/1996",
   "HT": "187cm",
   "WT": "87kg",
   "Games (W-D-L)": "7 (2-0-5)",
   "Goals": 1,
   "Seasons": "2015-2016",
   "Debut": "18y 293d",
   "Last": "19y 216d"
 },
 {
   "Cap": 60,
   "#": 38,
   "Player": "Clarke, Nathan",
   "DOB": "27/10/1979",
   "HT": "186cm",
   "WT": "80kg",
   "Games (W-D-L)": "6 (3-0-3)",
   "Goals": 4,
   "Seasons": "2000-2001",
   "Debut": "20y 256d",
   "Last": "21y 176d"
 },
 {
   "Cap": 166,
   "#": 45,
   "Player": "Bourke, Jordon",
   "DOB": "11/11/1994",
   "HT": "193cm",
   "WT": "88kg",
   "Games (W-D-L)": "6 (0-0-6)",
   "Goals": 2,
   "Seasons": "2014-2015",
   "Debut": "19y 292d",
   "Last": "20y 243d"
 },
 {
   "Cap": 173,
   "#": 48,
   "Player": "Beasley, Hugh",
   "DOB": "12/11/1995",
   "HT": "190cm",
   "WT": "86kg",
   "Games (W-D-L)": "6 (0-0-6)",
   "Goals": null,
   "Seasons": "2015",
   "Debut": "19y 207d",
   "Last": "19y 290d"
 },
 {
   "Cap": 200,
   "#": 41,
   "Player": "Eagles, Matt",
   "DOB": "9/02/1990",
   "HT": "200cm",
   "WT": "99kg",
   "Games (W-D-L)": "6 (3-0-3)",
   "Goals": 1,
   "Seasons": "2018, 2020",
   "Debut": "28y 86d",
   "Last": "30y 188d"
 },
 {
   "Cap": 31,
   "#": 37,
   "Player": "Carter, Nick",
   "DOB": "28/04/1978",
   "HT": "179cm",
   "WT": "86kg",
   "Games (W-D-L)": "5 (0-0-5)",
   "Goals": 1,
   "Seasons": "1997-1998",
   "Debut": "19y 13d",
   "Last": "20y 95d"
 },
 {
   "Cap": 32,
   "#": 40,
   "Player": "Clayton, Shane",
   "DOB": "24/10/1978",
   "HT": "186cm",
   "WT": "87kg",
   "Games (W-D-L)": "5 (1-0-4)",
   "Goals": null,
   "Seasons": "1997-1998",
   "Debut": "18y 199d",
   "Last": "19y 275d"
 },
 {
   "Cap": 68,
   "#": 35,
   "Player": "Morrison, Shane",
   "DOB": "10/01/1981",
   "HT": "193cm",
   "WT": "90kg",
   "Games (W-D-L)": "5 (4-1-0)",
   "Goals": null,
   "Seasons": "2002-2003",
   "Debut": "21y 114d",
   "Last": "22y 127d"
 },
 {
   "Cap": 82,
   "#": 34,
   "Player": "Attard, Jayden",
   "DOB": "27/02/1986",
   "HT": "187cm",
   "WT": "83kg",
   "Games (W-D-L)": "5 (1-0-4)",
   "Goals": 1,
   "Seasons": "2005-2006",
   "Debut": "19y 48d",
   "Last": "20y 69d"
 },
 {
   "Cap": 99,
   "#": 42,
   "Player": "Allan, Marcus",
   "DOB": "23/05/1986",
   "HT": "180cm",
   "WT": "75kg",
   "Games (W-D-L)": "5 (2-0-3)",
   "Goals": 1,
   "Seasons": "2006-2007",
   "Debut": "20y 81d",
   "Last": "21y 17d"
 },
 {
   "Cap": 224,
   "#": 29,
   "Player": "Tunstill, James",
   "DOB": "18/07/2003",
   "HT": "187cm",
   "WT": "75kg",
   "Games (W-D-L)": "5 (1-0-4)",
   "Goals": 1,
   "Seasons": "2022-2023",
   "Debut": "18y 340d",
   "Last": "20y 11d"
 },
 {
   "Cap": 231,
   "#": 41,
   "Player": "Joyce, Darragh",
   "DOB": "23/04/1997",
   "HT": "195cm",
   "WT": "90kg",
   "Games (W-D-L)": "5 (4-0-1)",
   "Goals": null,
   "Seasons": "2023",
   "Debut": "25y 335d",
   "Last": "25y 364d"
 },
 {
   "Cap": 72,
   "#": 31,
   "Player": "Weller, Luke",
   "DOB": "13/01/1982",
   "HT": "190cm",
   "WT": "93kg",
   "Games (W-D-L)": "4 (1-0-3)",
   "Goals": 1,
   "Seasons": "2003",
   "Debut": "21y 153d",
   "Last": "21y 194d"
 },
 {
   "Cap": 53,
   "#": 30,
   "Player": "Carey, Stefan",
   "DOB": "25/01/1976",
   "HT": "197cm",
   "WT": "104kg",
   "Games (W-D-L)": "3 (1-0-2)",
   "Goals": 1,
   "Seasons": "2000",
   "Debut": "24y 48d",
   "Last": "24y 60d"
 },
 {
   "Cap": 76,
   "#": 37,
   "Player": "Pratt, Daniel",
   "DOB": "21/03/1983",
   "HT": "186cm",
   "WT": "88kg",
   "Games (W-D-L)": "3 (1-0-2)",
   "Goals": 1,
   "Seasons": "2004",
   "Debut": "21y 62d",
   "Last": "21y 90d"
 },
 {
   "Cap": 80,
   "#": 4,
   "Player": "Logan, Tom",
   "DOB": "2/07/1985",
   "HT": "183cm",
   "WT": "83kg",
   "Games (W-D-L)": "3 (0-0-3)",
   "Goals": null,
   "Seasons": "2005",
   "Debut": "19y 274d",
   "Last": "20y 28d"
 },
 {
   "Cap": 86,
   "#": 24,
   "Player": "Spaanderman, Llane",
   "DOB": "10/02/1986",
   "HT": "198cm",
   "WT": "99kg",
   "Games (W-D-L)": "3 (1-0-2)",
   "Goals": 1,
   "Seasons": "2005",
   "Debut": "19y 79d",
   "Last": "19y 191d"
 },
 {
   "Cap": 104,
   "#": 40,
   "Player": "Hamill, Will",
   "DOB": "26/07/1986",
   "HT": "189cm",
   "WT": "74kg",
   "Games (W-D-L)": "3 (3-0-0)",
   "Goals": 1,
   "Seasons": "2007",
   "Debut": "20y 346d",
   "Last": "20y 361d"
 },
 {
   "Cap": 132,
   "#": 46,
   "Player": "McCauley, Broc",
   "DOB": "20/12/1986",
   "HT": "202cm",
   "WT": "98kg",
   "Games (W-D-L)": "3 (0-0-3)",
   "Goals": null,
   "Seasons": "2011",
   "Debut": "24y 104d",
   "Last": "24y 131d"
 },
 {
   "Cap": 145,
   "#": 48,
   "Player": "Wrigley, Stephen",
   "DOB": "18/04/1987",
   "HT": "187cm",
   "WT": "83kg",
   "Games (W-D-L)": "3 (0-0-3)",
   "Goals": null,
   "Seasons": "2012",
   "Debut": "25y 102d",
   "Last": "25y 115d"
 },
 {
   "Cap": 153,
   "#": 46,
   "Player": "Michael, Sam",
   "DOB": "5/07/1993",
   "HT": "199cm",
   "WT": "98kg",
   "Games (W-D-L)": "3 (0-0-3)",
   "Goals": null,
   "Seasons": "2013",
   "Debut": "19y 324d",
   "Last": "20y 57d"
 },
 {
   "Cap": 169,
   "#": 29,
   "Player": "McGrath, Jaden",
   "DOB": "15/06/1996",
   "HT": "180cm",
   "WT": "73kg",
   "Games (W-D-L)": "3 (0-0-3)",
   "Goals": null,
   "Seasons": "2015",
   "Debut": "18y 293d",
   "Last": "18y 307d"
 },
 {
   "Cap": 184,
   "#": 47,
   "Player": "William, Reuben",
   "DOB": "31/12/1997",
   "HT": "189cm",
   "WT": "87kg",
   "Games (W-D-L)": "3 (1-0-2)",
   "Goals": null,
   "Seasons": "2016",
   "Debut": "18y 191d",
   "Last": "18y 206d"
 },
 {
   "Cap": 194,
   "#": 21,
   "Player": "Skinner, Sam",
   "DOB": "29/06/1997",
   "HT": "197cm",
   "WT": "94kg",
   "Games (W-D-L)": "3 (1-0-2)",
   "Goals": 3,
   "Seasons": "2017, 2020",
   "Debut": "20y 31d",
   "Last": "23y 36d"
 },
 {
   "Cap": 206,
   "#": 22,
   "Player": "Hinge, Mitch",
   "DOB": "26/06/1998",
   "HT": "190cm",
   "WT": "84kg",
   "Games (W-D-L)": "3 (2-0-1)",
   "Goals": 1,
   "Seasons": "2019-2020",
   "Debut": "20y 326d",
   "Last": "22y 79d"
 },
 {
   "Cap": 213,
   "#": 38,
   "Player": "Ballenden, Connor",
   "DOB": "29/03/1999",
   "HT": "200cm",
   "WT": "101kg",
   "Games (W-D-L)": "3 (2-0-1)",
   "Goals": 1,
   "Seasons": "2020-2021",
   "Debut": "21y 124d",
   "Last": "22y 3d"
 },
 {
   "Cap": 33,
   "#": 21,
   "Player": "Green, Brent",
   "DOB": "29/03/1976",
   "HT": "197cm",
   "WT": "94kg",
   "Games (W-D-L)": "2 (0-1-1)",
   "Goals": null,
   "Seasons": "1997",
   "Debut": "21y 43d",
   "Last": "21y 140d"
 },
 {
   "Cap": 55,
   "#": 29,
   "Player": "Rusca, Shannon",
   "DOB": "20/08/1980",
   "HT": "182cm",
   "WT": "82kg",
   "Games (W-D-L)": "2 (0-0-2)",
   "Goals": null,
   "Seasons": "2000",
   "Debut": "19y 218d",
   "Last": "19y 226d"
 },
 {
   "Cap": 73,
   "#": 7,
   "Player": "Gram, Jason",
   "DOB": "27/04/1984",
   "HT": "186cm",
   "WT": "88kg",
   "Games (W-D-L)": "2 (1-0-1)",
   "Goals": null,
   "Seasons": "2003",
   "Debut": "19y 62d",
   "Last": "19y 69d"
 },
 {
   "Cap": 89,
   "#": 46,
   "Player": "Baird, Travis",
   "DOB": "25/07/1986",
   "HT": "193cm",
   "WT": "83kg",
   "Games (W-D-L)": "2 (1-0-1)",
   "Goals": 1,
   "Seasons": "2005",
   "Debut": "19y 13d",
   "Last": "19y 20d"
 },
 {
   "Cap": 101,
   "#": 13,
   "Player": "Schmidt, Chris",
   "DOB": "20/03/1989",
   "HT": "189cm",
   "WT": "85kg",
   "Games (W-D-L)": "2 (0-1-1)",
   "Goals": null,
   "Seasons": "2007",
   "Debut": "18y 74d",
   "Last": "18y 81d"
 },
 {
   "Cap": 112,
   "#": 41,
   "Player": "Clouston, Scott",
   "DOB": "2/02/1987",
   "HT": "193cm",
   "WT": "91kg",
   "Games (W-D-L)": "2 (0-0-2)",
   "Goals": 1,
   "Seasons": "2008",
   "Debut": "21y 182d",
   "Last": "21y 210d"
 },
 {
   "Cap": 186,
   "#": 19,
   "Player": "Clayton, Josh",
   "DOB": "17/01/1996",
   "HT": "190cm",
   "WT": "80kg",
   "Games (W-D-L)": "2 (0-0-2)",
   "Goals": null,
   "Seasons": "2016",
   "Debut": "20y 217d",
   "Last": "20y 224d"
 },
 {
   "Cap": 188,
   "#": 45,
   "Player": "Frost, Jack",
   "DOB": "25/02/1992",
   "HT": "195cm",
   "WT": "90kg",
   "Games (W-D-L)": "2 (0-0-2)",
   "Goals": null,
   "Seasons": "2017",
   "Debut": "25y 35d",
   "Last": "25y 43d"
 },
 {
   "Cap": 16,
   "#": 19,
   "Player": "McLean, Michael",
   "DOB": "3/03/1965",
   "HT": "180cm",
   "WT": "84kg",
   "Games (W-D-L)": "1 (0-0-1)",
   "Goals": null,
   "Seasons": "1997",
   "Debut": "32y 27d",
   "Last": "32y 27d"
 },
 {
   "Cap": 47,
   "#": 30,
   "Player": "Wirth, Derek",
   "DOB": "29/11/1978",
   "HT": "193cm",
   "WT": "94kg",
   "Games (W-D-L)": "1 (0-0-1)",
   "Goals": 2,
   "Seasons": "1998",
   "Debut": "19y 245d",
   "Last": "19y 245d"
 },
 {
   "Cap": 69,
   "#": 37,
   "Player": "Bradshaw, Darren",
   "DOB": "5/11/1980",
   "HT": "185cm",
   "WT": "90kg",
   "Games (W-D-L)": "1 (1-0-0)",
   "Goals": null,
   "Seasons": "2002",
   "Debut": "21y 250d",
   "Last": "21y 250d"
 },
 {
   "Cap": 88,
   "#": 32,
   "Player": "Ryswyk, Leigh",
   "DOB": "16/01/1985",
   "HT": "180cm",
   "WT": "74kg",
   "Games (W-D-L)": "1 (1-0-0)",
   "Goals": null,
   "Seasons": "2005",
   "Debut": "20y 139d",
   "Last": "20y 139d"
 },
 {
   "Cap": 103,
   "#": 45,
   "Player": "Dzufer, Daniel",
   "DOB": "21/01/1988",
   "HT": "188cm",
   "WT": "83kg",
   "Games (W-D-L)": "1 (0-0-1)",
   "Goals": null,
   "Seasons": "2007",
   "Debut": "19y 160d",
   "Last": "19y 160d"
 },
 {
   "Cap": 128,
   "#": 15,
   "Player": "Clarke, Xavier",
   "DOB": "28/09/1983",
   "HT": "182cm",
   "WT": "78kg",
   "Games (W-D-L)": "1 (0-0-1)",
   "Goals": null,
   "Seasons": "2010",
   "Debut": "26y 306d",
   "Last": "26y 306d"
 },
 {
   "Cap": 139,
   "#": 27,
   "Player": "Dyson, Josh",
   "DOB": "12/08/1991",
   "HT": "181cm",
   "WT": "71kg",
   "Games (W-D-L)": "1 (0-0-1)",
   "Goals": null,
   "Seasons": "2011",
   "Debut": "19y 360d",
   "Last": "19y 360d"
 },
 {
   "Cap": 225,
   "#": 39,
   "Player": "Michael, Carter",
   "DOB": "22/05/2002",
   "HT": "188cm",
   "WT": "83kg",
   "Games (W-D-L)": "1 (0-0-1)",
   "Goals": 1,
   "Seasons": "2022",
   "Debut": "20y 49d",
   "Last": "20y 49d"
 }
]